piiip/__init__.py
piiip/__main__.py
piiip/_logger.py
piiip/cache.py
piiip/cmd.py
piiip/intended_name_generator.py
piiip/package.py
piiip/py.typed
piiip/resources/tokens_selection.txt
piiip/resources/us_to_uk.json
piiip/tests/__init__.py
piiip/tests/test_intended_name_generator.py
piiip-1.0.0.dist-info/LICENSE
piiip-1.0.0.dist-info/METADATA
piiip-1.0.0.dist-info/WHEEL
piiip-1.0.0.dist-info/entry_points.txt
piiip-1.0.0.dist-info/top_level.txt
piiip-1.0.0.dist-info/RECORD
