Metadata-Version: 2.1
Name: piiip
Version: 1.0.0
Summary: Piiip Interactively Installs Intended Packages
Author: TNO Software and System Security
License: Apache License, Version 2.0
Project-URL: Homepage, https://github.com/TNO-S3/piiip
Platform: any
Classifier: Programming Language :: Python :: 3
Classifier: Operating System :: OS Independent
Classifier: Development Status :: 5 - Production/Stable
Classifier: Intended Audience :: Developers
Classifier: Topic :: Software Development :: Build Tools
Classifier: Topic :: Security
Classifier: Topic :: Software Development :: Libraries :: Python Modules
Classifier: Typing :: Typed
Requires-Python: >=3.8
License-File: LICENSE
Requires-Dist: requests
Requires-Dist: tenacity
Requires-Dist: importlib-resources ; python_version < "3.10"
